pyexif/__init__.py
pyexif/pyexif.py
pyexif-1.0.0.dist-info/LICENSE.txt
pyexif-1.0.0.dist-info/WHEEL
pyexif-1.0.0.dist-info/METADATA
pyexif-1.0.0.dist-info/RECORD
