Metadata-Version: 2.1
Name: pyexif
Version: 1.0.0
Summary: Python wrapping for the exiftool library
License: Apache 2.0
Author: EdLeafe
Author-email: ed@leafe.com
Requires-Python: >=3.8,<4.0
Classifier: License :: Other/Proprietary License
Classifier: Programming Language :: Python :: 3
Classifier: Programming Language :: Python :: 3.8
Classifier: Programming Language :: Python :: 3.9
Requires-Dist: click (>=8.1.3,<9.0.0)
